<?xml version="1.0" encoding='Windows-31J'?>
<!DOCTYPE ViewObject SYSTEM "jbo_03_01.dtd">

<ViewObject
   Name="XxpoResultsSearchVO"
   BindingStyle="Oracle"
   CustomQuery="true"
   RowClass="oracle.apps.fnd.framework.server.OAViewRowImpl"
   ComponentClass="itoen.oracle.apps.xxpo.xxpo320001j.server.XxpoResultsSearchVOImpl"
   MsgBundleClass="oracle.jbo.common.JboResourceBundle"
   FetchMode="FETCH_AS_NEEDED"
   Passivate="All"
   UseGlueCode="false" >
   <DesignTime>
      <Attr Name="_version" Value="9.0.3.14.00" />
      <Attr Name="_CodeGenFlagNew" Value="36" />
   </DesignTime>
   <ViewAttribute
      Name="RowKey"
      IsQueriable="false"
      IsPersistent="false"
      Precision="255"
      Type="java.lang.String"
      ColumnType="VARCHAR2"
      AliasName="VIEW_ATTR"
      SQLType="VARCHAR" >
   </ViewAttribute>
   <ViewAttribute
      Name="PeopleCode"
      IsQueriable="false"
      IsPersistent="false"
      Precision="255"
      Type="java.lang.String"
      ColumnType="VARCHAR2"
      AliasName="VIEW_ATTR"
      SQLType="VARCHAR" >
   </ViewAttribute>
   <ViewAttribute
      Name="OutSideUsrVendorId"
      IsQueriable="false"
      IsPersistent="false"
      Precision="255"
      Type="oracle.jbo.domain.Number"
      ColumnType="VARCHAR2"
      AliasName="VIEW_ATTR"
      SQLType="NUMERIC" >
   </ViewAttribute>
   <ViewAttribute
      Name="OutSideUsrVendorCode"
      IsQueriable="false"
      IsPersistent="false"
      Precision="255"
      Type="java.lang.String"
      ColumnType="VARCHAR2"
      AliasName="VIEW_ATTR"
      SQLType="VARCHAR" >
   </ViewAttribute>
   <ViewAttribute
      Name="OutSideUsrVendorName"
      IsQueriable="false"
      IsPersistent="false"
      Precision="255"
      Type="java.lang.String"
      ColumnType="VARCHAR2"
      AliasName="VIEW_ATTR"
      SQLType="VARCHAR" >
   </ViewAttribute>
   <ViewAttribute
      Name="VendorName"
      IsQueriable="false"
      IsPersistent="false"
      Precision="255"
      Type="java.lang.String"
      ColumnType="VARCHAR2"
      AliasName="VIEW_ATTR"
      Passivate="true"
      SQLType="VARCHAR" >
   </ViewAttribute>
   <ViewAttribute
      Name="DeliveryDateFrom"
      IsQueriable="false"
      IsPersistent="false"
      Type="oracle.jbo.domain.Date"
      ColumnType="Date"
      AliasName="VIEW_ATTR"
      SQLType="DATE" >
   </ViewAttribute>
   <ViewAttribute
      Name="MediatorName"
      IsQueriable="false"
      IsPersistent="false"
      Precision="255"
      Type="java.lang.String"
      ColumnType="VARCHAR2"
      AliasName="VIEW_ATTR"
      SQLType="VARCHAR" >
   </ViewAttribute>
   <ViewAttribute
      Name="LocationName"
      IsQueriable="false"
      IsPersistent="false"
      Precision="255"
      Type="java.lang.String"
      ColumnType="VARCHAR2"
      AliasName="VIEW_ATTR"
      SQLType="VARCHAR" >
   </ViewAttribute>
   <ViewAttribute
      Name="DepartmentName"
      IsQueriable="false"
      IsPersistent="false"
      Precision="255"
      Type="java.lang.String"
      ColumnType="VARCHAR2"
      AliasName="VIEW_ATTR"
      SQLType="VARCHAR" >
   </ViewAttribute>
   <ViewAttribute
      Name="OutSideUsrFactoryCode"
      IsPersistent="false"
      Precision="255"
      Type="java.lang.String"
      ColumnType="VARCHAR2"
      AliasName="VIEW_ATTR"
      SQLType="VARCHAR" >
   </ViewAttribute>
   <ViewAttribute
      Name="DeliveryDateTo"
      IsQueriable="false"
      IsPersistent="false"
      Type="oracle.jbo.domain.Date"
      ColumnType="DATE"
      AliasName="VIEW_ATTR"
      SQLType="DATE" >
   </ViewAttribute>
   <ViewAttribute
      Name="PoNum"
      IsPersistent="false"
      Precision="12"
      Type="java.lang.String"
      ColumnType="VARCHAR2"
      AliasName="VIEW_ATTR"
      SQLType="VARCHAR" >
   </ViewAttribute>
   <AttrArray Name="KeyAttributes">
      <Item Value="RowKey" />
   </AttrArray>
</ViewObject>
